LICENSE
MANIFEST.in
README.md
requirements.txt
setup.cfg
setup.py
srai_chat/__init__.py
srai_chat/command_base.py
srai_chat/mode_base.py
srai_chat/skill_base.py
srai_chat.egg-info/PKG-INFO
srai_chat.egg-info/SOURCES.txt
srai_chat.egg-info/dependency_links.txt
srai_chat.egg-info/requires.txt
srai_chat.egg-info/top_level.txt
srai_chat/skill/__init__.py
srai_chat/skill/mode_chat_gpt.py
srai_chat/skill/scedule.py
srai_chat/skill/skill_image_tag.py
srai_chat/skill/skill_mode_tools.py