Metadata-Version: 2.1
Name: srai-chat
Version: 0.1.4
Summary: A chat library frontend for srai services.
Home-page: https://github.com/southriverai/srai-chat
Author: Jaap Oosterbroek
Author-email: jaap.oosterbroek@southriverai.com
License: MIT
Download-URL: https://github.com/southriverai/srai-chat/archive/v_01.tar.gz
Keywords: SRAI,TOOLS
Platform: UNKNOWN
Classifier: Development Status :: 3 - Alpha
Classifier: Intended Audience :: Developers
Classifier: Topic :: Software Development :: Build Tools
Classifier: License :: OSI Approved :: MIT License
Classifier: Operating System :: OS Independent
Classifier: Programming Language :: Python :: 3
Requires-Python: >=3.5
License-File: LICENSE
